xlsxwriter_celldsl/__init__.py
xlsxwriter_celldsl/cell_dsl.py
xlsxwriter_celldsl/errors.py
xlsxwriter_celldsl/formats.py
xlsxwriter_celldsl/utils.py
xlsxwriter_celldsl/ops/__init__.py
xlsxwriter_celldsl/ops/classes.py
xlsxwriter_celldsl/ops/instances.py
xlsxwriter_celldsl/ops/traits.py
xlsxwriter_celldsl-0.6.0.dist-info/LICENSE
xlsxwriter_celldsl-0.6.0.dist-info/METADATA
xlsxwriter_celldsl-0.6.0.dist-info/WHEEL
xlsxwriter_celldsl-0.6.0.dist-info/top_level.txt
xlsxwriter_celldsl-0.6.0.dist-info/RECORD
