Metadata-Version: 2.1
Name: xlsxwriter-celldsl
Version: 0.6.0
Summary: A library to write scripts for generating Excel files using XlsxWriter in a more structured manner by avoiding dealing with absolute coordinates.
Home-page: https://github.com/DeltaEpsilon7787/xlsxwriter-celldsl
Author: DeltaEpsilon7787
Author-email: deltaepsilon7787@gmail.com
License: MIT
Platform: UNKNOWN
Requires-Python: >=3.6
Requires-Dist: attrs
Requires-Dist: xlsxwriter
Provides-Extra: testing
Requires-Dist: pytest ; extra == 'testing'
Requires-Dist: pytest-mock ; extra == 'testing'
